easul/__init__.py
easul/action.py
easul/data.py
easul/decision.py
easul/driver.py
easul/error.py
easul/expression.py
easul/notebook.py
easul/outcome.py
easul/process.py
easul/run.py
easul/source.py
easul/state.py
easul/step.py
easul/util.py
easul/algorithm/__init__.py
easul/algorithm/algorithm.py
easul/algorithm/factor.py
easul/algorithm/logic.py
easul/algorithm/predictive.py
easul/algorithm/result.py
easul/engine/__init__.py
easul/engine/client.py
easul/engine/codec.py
easul/engine/db.py
easul/engine/engine.py
easul/engine/execute.py
easul/engine/http.py
easul/engine/local.py
easul/engine/memory.py
easul/engine/redis.py
easul/engine/sqlite.py
easul/examples/__init__.py
easul/examples/examples.py
easul/examples/data/admission.csv
easul/examples/data/catheter.csv
easul/examples/data/progression.csv
easul/manage/__init__.py
easul/manage/monitor.py
easul/manage/regenerate.py
easul/plan/__init__.py
easul/plan/_plan.py
easul/plan/repo.py
easul/server/__init__.py
easul/server/models.py
easul/templates/__init__.py
easul/templates/dataset_fields.html
easul/templates/encoded_image.html
easul/templates/factor_table.html
easul/templates/lime_reasons.html
easul/templates/lime_table_plot.html
easul/tests/__init__.py
easul/tests/conftest.py
easul/tests/example.py
easul/tests/fixtures.py
easul/tests/pytest.ini
easul/tests/test_data.py
easul/tests/test_engine.py
easul/tests/test_notebook.py
easul/tests/test_process.py
easul/tests/test_step.py
easul/tests/test_util.py
easul/tests/algorithm/__init__.py
easul/tests/algorithm/test_logic.py
easul/tests/algorithm/test_predictive.py
easul/tests/engine/__init__.py
easul/tests/engine/test_codec.py
easul/tests/engine/test_local.py
easul/tests/jobs/__init__.py
easul/tests/plan/__init__.py
easul/tests/plan/test_creation.py
easul/tests/plan/test_metadata_store.py
easul/tests/plan/test_run.py
easul/tests/support/charlson_weights.csv
easul/tests/support/diabetes.txt
easul/tests/support/metadata/diabetes.eal
easul-1.0.3.dist-info/LICENSE.md
easul-1.0.3.dist-info/METADATA
easul-1.0.3.dist-info/WHEEL
easul-1.0.3.dist-info/top_level.txt
easul-1.0.3.dist-info/RECORD
