Metadata-Version: 2.1
Name: easul
Version: 1.0.3
Summary: Embeddable AI and State-based Understandable Logic toolkit
Home-page: https://github.com/rcfgroup/easul
Author: Rob Free
Author-email: rcfree@pm.me
License: LGPLv3
Project-URL: Bug Tracker, https://github.com/rcfgroup/easul/issues
Project-URL: Changelog, https://github.com/rcfgroup/easul/blob/main/CHANGELOG.md
Keywords: {keywords}
Platform: any
Classifier: Intended Audience :: Developers
Classifier: Intended Audience :: Science/Research
Classifier: License :: OSI Approved :: GNU Lesser General Public License v3 (LGPLv3)
Classifier: Operating System :: OS Independent
Classifier: Programming Language :: Python
Classifier: Programming Language :: Python :: 3.8
Classifier: Programming Language :: Python :: 3.9
Classifier: Programming Language :: Python :: 3.10
Classifier: Programming Language :: Python :: 3.11
Classifier: Topic :: Scientific/Engineering :: Artificial Intelligence
Classifier: Topic :: Scientific/Engineering :: Medical Science Apps.
Classifier: Topic :: Scientific/Engineering :: Visualization
Requires-Python: >=3.8
License-File: LICENSE.md
Requires-Dist: stringcase
Requires-Dist: PyYaml
Requires-Dist: Cerberus
Requires-Dist: pandas
Requires-Dist: dominate
Requires-Dist: jinja2
Requires-Dist: pillow <=9.5.0
Requires-Dist: scikit-learn <=1.2.2
Requires-Dist: dill <=0.3.6
Requires-Dist: matplotlib <=3.7.1
Requires-Dist: lime
Requires-Dist: numpy <=1.24.3
Requires-Dist: colour
Requires-Dist: attrs
Requires-Dist: anys
Requires-Dist: pytest
Requires-Dist: typer
Requires-Dist: msgpack
Provides-Extra: all
Provides-Extra: dev
Requires-Dist: pytest ; extra == 'dev'
Requires-Dist: pytest-cov ; extra == 'dev'
Requires-Dist: pytest-mock ; extra == 'dev'
Requires-Dist: twine ; extra == 'dev'
Requires-Dist: wheel ; extra == 'dev'
Provides-Extra: docs
Provides-Extra: tests
Requires-Dist: pytest ; extra == 'tests'
Requires-Dist: pytest-cov ; extra == 'tests'
Requires-Dist: pytest-mock ; extra == 'tests'
